netius/__init__.py
netius/adapters/__init__.py
netius/adapters/base.py
netius/adapters/fs.py
netius/adapters/memory.py
netius/adapters/mongo.py
netius/adapters/null.py
netius/auth/__init__.py
netius/auth/address.py
netius/auth/allow.py
netius/auth/base.py
netius/auth/deny.py
netius/auth/dummy.py
netius/auth/memory.py
netius/auth/passwd.py
netius/auth/simple.py
netius/base/__init__.py
netius/base/agent.py
netius/base/async_neo.py
netius/base/async_old.py
netius/base/asynchronous.py
netius/base/client.py
netius/base/common.py
netius/base/compat.py
netius/base/config.py
netius/base/conn.py
netius/base/container.py
netius/base/diag.py
netius/base/errors.py
netius/base/legacy.py
netius/base/log.py
netius/base/observer.py
netius/base/poll.py
netius/base/protocol.py
netius/base/request.py
netius/base/server.py
netius/base/service.py
netius/base/stream.py
netius/base/tls.py
netius/base/transport.py
netius/base/util.py
netius/base/extras/dh.pem
netius/base/extras/net.ca
netius/base/extras/net.cer
netius/base/extras/net.key
netius/base/extras/net.pub
netius/clients/__init__.py
netius/clients/apn.py
netius/clients/dht.py
netius/clients/dns.py
netius/clients/http.py
netius/clients/mjpg.py
netius/clients/raw.py
netius/clients/smtp.py
netius/clients/ssdp.py
netius/clients/torrent.py
netius/clients/ws.py
netius/common/__init__.py
netius/common/asn.py
netius/common/calc.py
netius/common/dhcp.py
netius/common/dkim.py
netius/common/ftp.py
netius/common/geo.py
netius/common/http.py
netius/common/http2.py
netius/common/mime.py
netius/common/parser.py
netius/common/pop.py
netius/common/rsa.py
netius/common/setup.py
netius/common/smtp.py
netius/common/socks.py
netius/common/stream.py
netius/common/structures.py
netius/common/style.py
netius/common/tftp.py
netius/common/tls.py
netius/common/torrent.py
netius/common/util.py
netius/common/ws.py
netius/examples/__init__.py
netius/examples/http.py
netius/examples/upnp.py
netius/extra/__init__.py
netius/extra/desktop.py
netius/extra/dhcp_s.py
netius-1.20.7.dist-info/LICENSE
netius-1.20.7.dist-info/METADATA
netius-1.20.7.dist-info/WHEEL
netius-1.20.7.dist-info/top_level.txt
netius-1.20.7.dist-info/RECORD
